README.rst
setup.py
firefox_shm/__init__.py
firefox_shm/__version__.py
firefox_shm.egg-info/PKG-INFO
firefox_shm.egg-info/SOURCES.txt
firefox_shm.egg-info/dependency_links.txt
firefox_shm.egg-info/not-zip-safe
firefox_shm.egg-info/top_level.txt
scripts/firefox-shm