Metadata-Version: 1.1
Name: firefox-shm
Version: 0.0.4
Summary: Helper scripts for my linux system.
Home-page: http://bitbucket.org/igraltist/firefox-shm
Author: Jens Kasten
Author-email: jens@kasten-edv.de
License: GNU GPLv3
Keywords: firefox tmpfs
Platform: UNKNOWN
Classifier: Development Status :: 4 - Beta
Classifier: Intended Audience :: System Administrators
Classifier: License :: OSI Approved :: GNU General Public License v3 (GPLv3)
Classifier: Operating System :: POSIX :: Linux
Classifier: Programming Language :: Python :: 3.3
Classifier: Topic :: System :: Systems Administration
